LICENSE.txt
MANIFEST.in
README.rst
setup.cfg
setup.py
django_publishing.egg-info/PKG-INFO
django_publishing.egg-info/SOURCES.txt
django_publishing.egg-info/dependency_links.txt
django_publishing.egg-info/requires.txt
django_publishing.egg-info/top_level.txt
project/__init__.py
project/manage.py
project/apps/__init__.py
project/apps/blog/__init__.py
project/apps/blog/admin.py
project/apps/blog/models.py
project/apps/blog/migrations/0001_initial.py
project/apps/blog/migrations/0002_auto_20160930_1118.py
project/apps/blog/migrations/0003_auto_20160930_1151.py
project/apps/blog/migrations/0004_auto_20160930_1156.py
project/apps/blog/migrations/0005_auto_20160930_1248.py
project/apps/blog/migrations/0006_auto_20160930_1257.py
project/apps/blog/migrations/__init__.py
project/project/__init__.py
project/project/settings.py
project/project/urls.py
project/project/wsgi.py
publishing/__init__.py
publishing/admin.py
publishing/mixins.py
publishing/models.py
publishing/utils.py
publishing/migrations/0001_initial.py
publishing/migrations/__init__.py
publishing/templates/admin/change_form.html
publishing/templates/admin/publish_change_form.html
publishing/templates/admin/publish_change_list.html