Metadata-Version: 1.1
Name: django-publishing
Version: 0.0.4
Summary: A simple django app to publish models with a workflow and permissions
Home-page: https://github.com/domenikjones/django-publishing
Author: Scholz & Volkmer (Domenik Jones)
Author-email: d.jones@s-v.de
License: MIT License
Download-URL: https://github.com/domenikjones/django-publishing/tarball/0.1
Keywords: django model moderation editorial development
Platform: UNKNOWN
Classifier: Development Status :: 3 - Alpha
Classifier: Intended Audience :: Developers
Classifier: License :: OSI Approved :: MIT License
Classifier: Programming Language :: Python :: 3.4
